djongo/__init__.py
djongo/admin.py
djongo/base.py
djongo/compiler.py
djongo/creation.py
djongo/cursor.py
djongo/database.py
djongo/exceptions.py
djongo/features.py
djongo/introspection.py
djongo/operations.py
djongo/schema.py
djongo/storage.py
djongo/transaction.py
djongo/models/__init__.py
djongo/models/fields.py
djongo/models/indexes.py
djongo/models/json.py
djongo/sql2mongo/__init__.py
djongo/sql2mongo/aggregation.py
djongo/sql2mongo/constraints.py
djongo/sql2mongo/converters.py
djongo/sql2mongo/functions.py
djongo/sql2mongo/operators.py
djongo/sql2mongo/query.py
djongo/sql2mongo/sql_tokens.py
djongo/sql2mongo/validation.py
djongo_fixed-1.3.7.dist-info/LICENSE
djongo_fixed-1.3.7.dist-info/METADATA
djongo_fixed-1.3.7.dist-info/WHEEL
djongo_fixed-1.3.7.dist-info/top_level.txt
djongo_fixed-1.3.7.dist-info/RECORD
