Metadata-Version: 2.1
Name: djongo-fixed
Version: 1.3.7
Summary: Driver for allowing Django to use MongoDB as the database backend.
Home-page: https://www.djongomapper.com/
Author: doableware
Author-email: support@doableware.com
License: AGPL
Keywords: Django MongoDB driver connector
Classifier: Development Status :: 3 - Alpha
Classifier: Intended Audience :: Developers
Classifier: License :: OSI Approved :: BSD License
Classifier: Programming Language :: Python :: 3.6
Requires-Python: >=3.6
License-File: LICENSE
Requires-Dist: sqlparse (==0.4.2)
Requires-Dist: pymongo (>=3.6.0)
Requires-Dist: django (>=2.1)
Provides-Extra: json
Requires-Dist: jsonfield (>=2.0.2) ; extra == 'json'
Requires-Dist: django-jsoneditor (>=0.0.12) ; extra == 'json'
